pint/__init__.py
pint/_typing.py
pint/babel_names.py
pint/compat.py
pint/constants_en.txt
pint/context.py
pint/converters.py
pint/default_en.txt
pint/definitions.py
pint/errors.py
pint/formatting.py
pint/matplotlib.py
pint/pint_convert.py
pint/pint_eval.py
pint/py.typed
pint/registry.py
pint/registry_helpers.py
pint/testing.py
pint/toktest.py
pint/util.py
pint/xtranslated.txt
pint/delegates/__init__.py
pint/delegates/base_defparser.py
pint/delegates/formatter/__init__.py
pint/delegates/formatter/_compound_unit_helpers.py
pint/delegates/formatter/_format_helpers.py
pint/delegates/formatter/_spec_helpers.py
pint/delegates/formatter/_to_register.py
pint/delegates/formatter/full.py
pint/delegates/formatter/html.py
pint/delegates/formatter/latex.py
pint/delegates/formatter/plain.py
pint/delegates/txt_defparser/__init__.py
pint/delegates/txt_defparser/block.py
pint/delegates/txt_defparser/common.py
pint/delegates/txt_defparser/context.py
pint/delegates/txt_defparser/defaults.py
pint/delegates/txt_defparser/defparser.py
pint/delegates/txt_defparser/group.py
pint/delegates/txt_defparser/plain.py
pint/delegates/txt_defparser/system.py
pint/facets/__init__.py
pint/facets/context/__init__.py
pint/facets/context/definitions.py
pint/facets/context/objects.py
pint/facets/context/registry.py
pint/facets/dask/__init__.py
pint/facets/group/__init__.py
pint/facets/group/definitions.py
pint/facets/group/objects.py
pint/facets/group/registry.py
pint/facets/measurement/__init__.py
pint/facets/measurement/objects.py
pint/facets/measurement/registry.py
pint/facets/nonmultiplicative/__init__.py
pint/facets/nonmultiplicative/definitions.py
pint/facets/nonmultiplicative/objects.py
pint/facets/nonmultiplicative/registry.py
pint/facets/numpy/__init__.py
pint/facets/numpy/numpy_func.py
pint/facets/numpy/quantity.py
pint/facets/numpy/registry.py
pint/facets/numpy/unit.py
pint/facets/plain/__init__.py
pint/facets/plain/definitions.py
pint/facets/plain/objects.py
pint/facets/plain/qto.py
Pint-0.24.3.dist-info/AUTHORS
Pint-0.24.3.dist-info/LICENSE
Pint-0.24.3.dist-info/METADATA
Pint-0.24.3.dist-info/WHEEL
Pint-0.24.3.dist-info/entry_points.txt
Pint-0.24.3.dist-info/top_level.txt
Pint-0.24.3.dist-info/RECORD
