Metadata-Version: 2.1
Name: Pint
Version: 0.24.3
Summary: Physical quantities module
Author-email: "Hernan E. Grecco" <hernan.grecco@gmail.com>
Maintainer-email: "Hernan E. Grecco" <hernan.grecco@gmail.com>, Jules Chéron <julescheron@gmail.com>
License: BSD
Project-URL: Homepage, https://github.com/hgrecco/pint
Project-URL: Documentation, https://pint.readthedocs.io/
Keywords: physical,quantities,unit,conversion,science
Classifier: Development Status :: 4 - Beta
Classifier: Intended Audience :: Developers
Classifier: Intended Audience :: Science/Research
Classifier: License :: OSI Approved :: BSD License
Classifier: Operating System :: MacOS :: MacOS X
Classifier: Operating System :: Microsoft :: Windows
Classifier: Operating System :: POSIX
Classifier: Programming Language :: Python
Classifier: Topic :: Scientific/Engineering
Classifier: Topic :: Software Development :: Libraries
Classifier: Programming Language :: Python :: 3.9
Classifier: Programming Language :: Python :: 3.10
Classifier: Programming Language :: Python :: 3.11
Classifier: Programming Language :: Python :: 3.12
Requires-Python: >=3.9
License-File: LICENSE
License-File: AUTHORS
Requires-Dist: appdirs>=1.4.4
Requires-Dist: typing_extensions
Requires-Dist: flexcache>=0.3
Requires-Dist: flexparser>=0.3
Provides-Extra: testbase
Requires-Dist: pytest; extra == "testbase"
Requires-Dist: pytest-cov; extra == "testbase"
Requires-Dist: pytest-subtests; extra == "testbase"
Requires-Dist: pytest-benchmark; extra == "testbase"
Provides-Extra: test
Requires-Dist: pytest; extra == "test"
Requires-Dist: pytest-mpl; extra == "test"
Requires-Dist: pytest-cov; extra == "test"
Requires-Dist: pytest-subtests; extra == "test"
Requires-Dist: pytest-benchmark; extra == "test"
Provides-Extra: bench
Requires-Dist: pytest; extra == "bench"
Requires-Dist: pytest-codspeed; extra == "bench"
Provides-Extra: numpy
Requires-Dist: numpy>=1.23; extra == "numpy"
Provides-Extra: uncertainties
Requires-Dist: uncertainties>=3.1.6; extra == "uncertainties"
Provides-Extra: babel
Requires-Dist: babel<=2.8; extra == "babel"
Provides-Extra: pandas
Requires-Dist: pint-pandas>=0.3; extra == "pandas"
Provides-Extra: xarray
Requires-Dist: xarray; extra == "xarray"
Provides-Extra: dask
Requires-Dist: dask; extra == "dask"
Provides-Extra: mip
Requires-Dist: mip>=1.13; extra == "mip"
